[
  {
    "id": "35c87deecae5d422",
    "username": "jovin",
    "password": "jovin256",
    "expiresAt": "2025-12-31",
    "allowOffline": true
  },
  {
    "id": "ed6ecefabfbd7af7",
    "username": "Hostman",
    "password": "09876",
    "expiresAt": "2025-12-31",
    "allowOffline": false
  },
  {
    "id": "4fb9138fdc5c5659",
    "username": "cyber",
    "password": "09876",
    "expiresAt": "2025-9-11",
    "allowOffline": false
  },
  {
    "id": "35c87deecae5d422",
    "username": "ikmodz",
    "password": "09876",
    "expiresAt": "2025-12-31",
    "allowOffline": false 
  },
  {
    "id": "8d9ec3e2ca36bafa",
    "username": "joker",
    "password": "88888",
    "expiresAt": "2025-11-30",
    "allowOffline": false
  },
  {
    "id": "93c0b1da615f54b7",
    "username": "angel",
    "password": "99999",
    "expiresAt": "2025-11-30",
    "allowOffline": false
  },
  {
    "id": "e085066fb34f21d4",
    "username": "assistant",
    "password": "202020",
    "expiresAt": "2025-7-7",
    "allowOffline": false
  },
  {
    "id": "3064601928149292",
    "username": "barnes",
    "password": "tech",
    "expiresAt": "2025-7-7",
    "allowOffline": false
  },
  {
    "id": "f4e32ffee2f1b235",
    "username": "dev256",
    "password": "99999",
    "expiresAt": "2025-7-7",
    "allowOffline": false
  },
  {
    "id": "3157e2b28d940df3",
    "username": "jr2pubg",
    "password": "99999",
    "expiresAt": "2025-8-7",
    "allowOffline": false
  },
  {
    "id": "684767ba1a4ff089",
    "username": "ceddrick",
    "password": "99999",
    "expiresAt": "2025-8-7",
    "allowOffline": false
  }
]
